buffering_queue_logger/__init__.py
buffering_queue_logger/core.py
buffering_queue_logger/handlers.py
buffering_queue_logger/listeners.py
buffering_queue_logger/send_logs_utils.py
buffering_queue_logger-0.3.0.dist-info/LICENSE
buffering_queue_logger-0.3.0.dist-info/METADATA
buffering_queue_logger-0.3.0.dist-info/WHEEL
buffering_queue_logger-0.3.0.dist-info/RECORD
