Metadata-Version: 2.1
Name: buffering-queue-logger
Version: 0.3.0
Summary: Helpers for sending logs to a destination in batches using a buffer in a queue alongside any Python app.
Home-page: https://github.com/Jaza/buffering-queue-logger
License: Apache-2.0
Author: Jeremy Epstein
Author-email: jazepstein@gmail.com
Requires-Python: >=3.10,<4
Classifier: License :: OSI Approved :: Apache Software License
Classifier: Programming Language :: Python :: 3
Classifier: Programming Language :: Python :: 3.10
Classifier: Programming Language :: Python :: 3.11
Requires-Dist: requests (>=2.28.2,<3.0.0)
